pyax/__init__.py
pyax/__main__.py
pyax/_cli.py
pyax/_constants.py
pyax/_highlighter.py
pyax/_mixin.py
pyax/_observer.py
pyax/_uielement.py
pyax/utils.py
pyax-0.3.3.dist-info/METADATA
pyax-0.3.3.dist-info/WHEEL
pyax-0.3.3.dist-info/entry_points.txt
pyax-0.3.3.dist-info/licenses/LICENSE
pyax-0.3.3.dist-info/RECORD
