Metadata-Version: 2.4
Name: pyax
Version: 0.3.3
Summary: Client library for macOS accessibility
Project-URL: Homepage, https://github.com/eeejay/pyax
Project-URL: Bug Tracker, https://github.com/eeejay/pyax/issues
Author-email: Eitan Isaacson <eitan@monotonous.org>
License-Expression: MIT
License-File: LICENSE
Classifier: Intended Audience :: Developers
Classifier: License :: OSI Approved :: MIT License
Classifier: Operating System :: MacOS :: MacOS X
Classifier: Programming Language :: Python :: 3
Requires-Python: >=3.7
Requires-Dist: pyobjc-framework-applicationservices>=10.1
Requires-Dist: typer>=0.20.0
Provides-Extra: highlight
Requires-Dist: pyqt6>=6.9.0; extra == 'highlight'
